{
    "display": {
      "icon": {
        "item": "minecraft:archer_pottery_sherd"
      },
      "title": "Archer Pottery Sherd",
      "description": "Obtain Archer Pottery Sherd",
      "frame": "task",
      "show_toast": true,
      "announce_to_chat": true,
      "hidden": false
    },
    "parent": "qfe:nature_and_loot/angler_pottery_sherd",
    "criteria": {
      "has_cobblestone": {
        "trigger": "minecraft:inventory_changed",
        "conditions": {
          "items": [
            {
              "items": ["minecraft:archer_pottery_sherd"],
              "count": {
                "min": 1,
                "max": 64
              }
            }
          ]
        }
      }
    },
    "rewards": {
      "function": "qfe:nature_and_loot/archer_pottery_sherd"
    }
  }