{
  "display": {
    "icon": {
      "item": "minecraft:zombie_head"
    },
    "title": "Zombie Head",
    "description": "Obtain Zombie Head",
    "frame": "task",
    "show_toast": true,
    "announce_to_chat": true,
    "hidden": false
  },
  "parent": "qfe:nature_and_loot/skeleton_skull",
  "criteria": {
    "has_obtained_item": {
      "trigger": "minecraft:inventory_changed",
      "conditions": {
        "items": [
          {
            "items": [
              "minecraft:zombie_head"
            ],
            "count": {
              "min": 1,
              "max": 64
            }
          }
        ]
      }
    }
  },
  "rewards": {
    "function": "qfe:advancements/nature_and_loot/zombie_head"
  }
}