{
  "display": {
    "icon": {
      "id": "minecraft:cyan_bundle"
    },
    "title": "Cyan Bundle",
    "description": "Obtain Cyan Bundle",
    "frame": "task",
    "show_toast": true,
    "announce_to_chat": true,
    "hidden": false
  },
  "parent": "qfe:tools_and_combat/green_bundle",
  "criteria": {
    "has_obtained_item": {
      "trigger": "minecraft:inventory_changed",
      "conditions": {
        "items": [
          {
            "items": [
              "minecraft:cyan_bundle"
            ],
            "count": {
              "min": 1,
              "max": 64
            }
          }
        ]
      }
    }
  },
  "rewards": {
    "function": "qfe:advancement/tools_and_combat/cyan_bundle"
  }
}