{
  "display": {
    "icon": {
      "id": "minecraft:warped_wart_block"
    },
    "title": "Warped Wart Block",
    "description": "Obtain Warped Wart Block",
    "frame": "task",
    "show_toast": true,
    "announce_to_chat": true,
    "hidden": false
  },
  "parent": "qfe:nether/warped_fungus",
  "criteria": {
    "has_obtained_item": {
      "trigger": "minecraft:inventory_changed",
      "conditions": {
        "items": [
          {
            "items": [
              "minecraft:warped_wart_block"
            ],
            "count": {
              "min": 1,
              "max": 64
            }
          }
        ]
      }
    }
  },
  "rewards": {
    "function": "qfe:advancements/nether/warped_wart_block"
  }
}