{
    "condition": "minecraft:entity_properties",
    "entity": "this",
    "predicate": {
      "type": "minecraft:player",
      "type_specific": {
        "type": "player",
        "advancements": {
          "qfe:manufactured/anvil": true,
          "qfe:manufactured/armor_stand": true,
          "qfe:manufactured/barrel": true,
          "qfe:manufactured/beacon": true,
          "qfe:manufactured/bell": true,
          "qfe:manufactured/black_candle": true,
          "qfe:manufactured/black_dye": true,
          "qfe:manufactured/blast_furnace": true,
          "qfe:manufactured/blue_candle": true,
          "qfe:manufactured/blue_dye": true,
          "qfe:manufactured/book": true,
          "qfe:manufactured/bookshelf": true,
          "qfe:manufactured/bowl": true,
          "qfe:manufactured/brick_slab": true,
          "qfe:manufactured/brick_stairs": true,
          "qfe:manufactured/brick_wall": true,
          "qfe:manufactured/brick": true,
          "qfe:manufactured/bricks": true,
          "qfe:manufactured/brown_candle": true,
          "qfe:manufactured/brown_dye": true,
          "qfe:manufactured/campfire": true,
          "qfe:manufactured/candle": true,
          "qfe:manufactured/cartography_table": true,
          "qfe:manufactured/chain": true,
          "qfe:manufactured/charcoal": true,
          "qfe:manufactured/chest": true,
          "qfe:manufactured/chipped_anvil": true,
          "qfe:manufactured/chiseled_bookshelf": true,
          "qfe:manufactured/composter": true,
          "qfe:manufactured/crafting_table": true,
          "qfe:manufactured/creeper_banner_pattern": true,
          "qfe:manufactured/cyan_candle": true,
          "qfe:manufactured/cyan_dye": true,
          "qfe:manufactured/damaged_anvil": true,
          "qfe:manufactured/decorated_pot": true,
          "qfe:manufactured/enchanted_book": true,
          "qfe:manufactured/enchanting_table": true,
          "qfe:manufactured/ender_chest": true,
          "qfe:manufactured/fire_charge": true,
          "qfe:manufactured/firework_rocket": true,
          "qfe:manufactured/firework_star": true,
          "qfe:manufactured/fletching_table": true,
          "qfe:manufactured/flower_banner_pattern": true,
          "qfe:manufactured/flower_pot": true,
          "qfe:manufactured/furnace": true,
          "qfe:manufactured/globe_banner_pattern": true,
          "qfe:manufactured/glow_item_frame": true,
          "qfe:manufactured/gray_candle": true,
          "qfe:manufactured/gray_dye": true,
          "qfe:manufactured/green_candle": true,
          "qfe:manufactured/green_dye": true,
          "qfe:manufactured/grindstone": true,
          "qfe:manufactured/heavy_weighted_pressure_plate": true,
          "qfe:manufactured/iron_bars": true,
          "qfe:manufactured/iron_door": true,
          "qfe:manufactured/iron_trapdoor": true,
          "qfe:manufactured/item_frame": true,
          "qfe:manufactured/jukebox": true,
          "qfe:manufactured/ladder": true,
          "qfe:manufactured/lantern": true,
          "qfe:manufactured/lectern": true,
          "qfe:manufactured/light_blue_candle": true,
          "qfe:manufactured/light_blue_dye": true,
          "qfe:manufactured/light_gray_candle": true,
          "qfe:manufactured/light_gray_dye": true,
          "qfe:manufactured/light_weighted_pressure_plate": true,
          "qfe:manufactured/lightning_rod": true,
          "qfe:manufactured/lime_candle": true,
          "qfe:manufactured/lime_dye": true,
          "qfe:manufactured/loom": true,
          "qfe:manufactured/magenta_candle": true,
          "qfe:manufactured/magenta_dye": true,
          "qfe:manufactured/mojang_banner_pattern": true,
          "qfe:manufactured/mud_brick_slab": true,
          "qfe:manufactured/mud_brick_stairs": true,
          "qfe:manufactured/mud_brick_wall": true,
          "qfe:manufactured/mud_bricks": true,
          "qfe:manufactured/nether_star": true,
          "qfe:manufactured/orange_candle": true,
          "qfe:manufactured/orange_dye": true,
          "qfe:manufactured/packed_mud": true,
          "qfe:manufactured/painting": true,
          "qfe:manufactured/paper": true,
          "qfe:manufactured/piglin_banner_pattern": true,
          "qfe:manufactured/pink_candle": true,
          "qfe:manufactured/pink_dye": true,
          "qfe:manufactured/purple_candle": true,
          "qfe:manufactured/purple_dye": true,
          "qfe:manufactured/red_candle": true,
          "qfe:manufactured/red_dye": true,
          "qfe:manufactured/scaffolding": true,
          "qfe:manufactured/skull_banner_pattern": true,
          "qfe:manufactured/smithing_table": true,
          "qfe:manufactured/smoker": true,
          "qfe:manufactured/stick": true,
          "qfe:manufactured/stonecutter": true,
          "qfe:manufactured/torch": true,
          "qfe:manufactured/white_candle": true,
          "qfe:manufactured/white_dye": true,
          "qfe:manufactured/writable_book": true,
          "qfe:manufactured/written_book": true,
          "qfe:manufactured/yellow_candle": true,
          "qfe:manufactured/yellow_dye": true
        }
      }
    }
  }