{
  "display": {
    "icon": {
      "id": "minecraft:leather"
    },
    "title": "Leather",
    "description": "Obtain Leather",
    "frame": "task",
    "show_toast": true,
    "announce_to_chat": true,
    "hidden": false
  },
  "parent": "qfe:loot/blue_egg",
  "criteria": {
    "has_obtained_item": {
      "trigger": "minecraft:inventory_changed",
      "conditions": {
        "items": [
          {
            "items": [
              "minecraft:leather"
            ],
            "count": {
              "min": 1,
              "max": 64
            }
          }
        ]
      }
    }
  },
  "rewards": {
    "function": "qfe:advancement/loot/leather"
  }
}