{
  "display": {
    "icon": {
      "id": "minecraft:gray_dye"
    },
    "title": "Gray Dye",
    "description": "Obtain Gray Dye",
    "frame": "task",
    "show_toast": true,
    "announce_to_chat": true,
    "hidden": false
  },
  "parent": "qfe:manufactured/black_dye",
  "criteria": {
    "has_obtained_item": {
      "trigger": "minecraft:inventory_changed",
      "conditions": {
        "items": [
          {
            "items": [
              "minecraft:gray_dye"
            ],
            "count": {
              "min": 1,
              "max": 64
            }
          }
        ]
      }
    }
  },
  "rewards": {
    "function": "qfe:advancements/manufactured/gray_dye"
  }
}