{
    "display": {
      "icon": {
        "item": "minecraft:dead_bubble_coral_block"
      },
      "title": "Dead Bubble Coral Block",
      "description": "Obtain Dead Bubble Coral Block",
      "frame": "goal",
      "show_toast": true,
      "announce_to_chat": true,
      "hidden": false
    },
    "parent": "qfe:ocean/bubble_coral_block",
    "criteria": {
      "has_cobblestone": {
        "trigger": "minecraft:inventory_changed",
        "conditions": {
          "items": [
            {
              "items": ["minecraft:dead_bubble_coral_block"],
              "count": {
                "min": 1,
                "max": 64
              }
            }
          ]
        }
      }
    },
    "rewards": {
      "function": "qfe:ocean/dead_bubble_coral_block"
    }
  }